phylotreelib.py
phylotreelib-1.32.1.dist-info/licenses/LICENSE
phylotreelib-1.32.1.dist-info/METADATA
phylotreelib-1.32.1.dist-info/WHEEL
phylotreelib-1.32.1.dist-info/top_level.txt
phylotreelib-1.32.1.dist-info/RECORD
