Metadata-Version: 2.4
Name: phylotreelib
Version: 1.32.1
Summary: Analyze and manipulate phylogenetic trees
Author-email: Anders Gorm Pedersen <agpe@dtu.dk>
Project-URL: Repository, https://github.com/agormp/phylotreelib
Classifier: License :: OSI Approved :: GNU General Public License v3 (GPLv3)
Classifier: Programming Language :: Python :: 3
Classifier: Operating System :: OS Independent
Requires-Python: >=3.6
License-File: LICENSE
Requires-Dist: numpy
Dynamic: license-file
